[{"pos": "1", "name": "Juventus", "pld": "11", "w": "9", "d": "2", "l": "0", "goals": "29:11", "diff": "18", "pts": "20:2"}, {"pos": "2", "name": "Calcio Padova", "pld": "11", "w": "5", "d": "5", "l": "1", "goals": "17:12", "diff": "5", "pts": "15:7"}, {"pos": "3", "name": "Inter", "pld": "11", "w": "6", "d": "2", "l": "3", "goals": "31:19", "diff": "12", "pts": "14:8"}, {"pos": "4", "name": "AC Milan", "pld": "11", "w": "6", "d": "2", "l": "3", "goals": "27:17", "diff": "10", "pts": "14:8"}, {"pos": "5", "name": "Calcio Como", "pld": "11", "w": "5", "d": "4", "l": "2", "goals": "17:14", "diff": "3", "pts": "14:8"}, {"pos": "6", "name": "ACF Fiorentina", "pld": "11", "w": "6", "d": "1", "l": "4", "goals": "26:17", "diff": "9", "pts": "13:9"}, {"pos": "7", "name": "Lazio Roma", "pld": "11", "w": "5", "d": "3", "l": "3", "goals": "21:13", "diff": "8", "pts": "13:9"}, {"pos": "8", "name": "Torino FC", "pld": "11", "w": "6", "d": "1", "l": "4", "goals": "24:21", "diff": "3", "pts": "13:9"}, {"pos": "9", "name": "Atalanta", "pld": "11", "w": "5", "d": "2", "l": "4", "goals": "24:20", "diff": "4", "pts": "12:10"}, {"pos": "10", "name": "Unione Triestina", "pld": "11", "w": "3", "d": "6", "l": "2", "goals": "18:21", "diff": "-3", "pts": "12:10"}, {"pos": "11", "name": "Sampdoria", "pld": "11", "w": "5", "d": "1", "l": "5", "goals": "25:19", "diff": "6", "pts": "11:11"}, {"pos": "12", "name": "Novara Calcio", "pld": "11", "w": "3", "d": "3", "l": "5", "goals": "19:20", "diff": "-1", "pts": "9:13"}, {"pos": "13", "name": "AS Roma", "pld": "11", "w": "4", "d": "1", "l": "6", "goals": "16:21", "diff": "-5", "pts": "9:13"}, {"pos": "14", "name": "US Palermo", "pld": "11", "w": "4", "d": "1", "l": "6", "goals": "14:19", "diff": "-5", "pts": "9:13"}, {"pos": "15", "name": "AS Bari", "pld": "11", "w": "4", "d": "1", "l": "6", "goals": "14:23", "diff": "-9", "pts": "9:13"}, {"pos": "16", "name": "Genoa CFC", "pld": "11", "w": "3", "d": "2", "l": "6", "goals": "12:17", "diff": "-5", "pts": "8:14"}, {"pos": "17", "name": "Lucchese", "pld": "11", "w": "2", "d": "4", "l": "5", "goals": "19:25", "diff": "-6", "pts": "8:14"}, {"pos": "18", "name": "Bologna FC", "pld": "11", "w": "1", "d": "5", "l": "5", "goals": "13:22", "diff": "-9", "pts": "7:15"}, {"pos": "19", "name": "Aurora Pro Patria", "pld": "11", "w": "2", "d": "3", "l": "6", "goals": "10:19", "diff": "-9", "pts": "7:15"}, {"pos": "20", "name": "AC Venezia", "pld": "11", "w": "1", "d": "1", "l": "9", "goals": "9:35", "diff": "-26", "pts": "3:19"}]