[{"pos": "1", "name": "ACF Fiorentina", "pld": "13", "w": "9", "d": "4", "l": "0", "goals": "26:7", "diff": "19", "pts": "22:4"}, {"pos": "2", "name": "Torino FC", "pld": "13", "w": "7", "d": "3", "l": "3", "goals": "22:11", "diff": "11", "pts": "17:9"}, {"pos": "3", "name": "AC Milan", "pld": "13", "w": "6", "d": "3", "l": "4", "goals": "29:19", "diff": "10", "pts": "15:11"}, {"pos": "4", "name": "Sampdoria", "pld": "13", "w": "7", "d": "1", "l": "5", "goals": "25:21", "diff": "4", "pts": "15:11"}, {"pos": "5", "name": "AS Roma", "pld": "13", "w": "4", "d": "7", "l": "2", "goals": "23:19", "diff": "4", "pts": "15:11"}, {"pos": "6", "name": "Lanerossi Vicenza", "pld": "13", "w": "5", "d": "5", "l": "3", "goals": "15:13", "diff": "2", "pts": "15:11"}, {"pos": "7", "name": "SSC Napoli", "pld": "13", "w": "4", "d": "6", "l": "3", "goals": "24:20", "diff": "4", "pts": "14:12"}, {"pos": "8", "name": "Calcio Padova", "pld": "13", "w": "6", "d": "2", "l": "5", "goals": "16:18", "diff": "-2", "pts": "14:12"}, {"pos": "9", "name": "Juventus", "pld": "13", "w": "4", "d": "6", "l": "3", "goals": "15:17", "diff": "-2", "pts": "14:12"}, {"pos": "10", "name": "Inter", "pld": "13", "w": "6", "d": "1", "l": "6", "goals": "22:17", "diff": "5", "pts": "13:13"}, {"pos": "11", "name": "Atalanta", "pld": "13", "w": "6", "d": "1", "l": "6", "goals": "26:25", "diff": "1", "pts": "13:13"}, {"pos": "12", "name": "SPAL 1907 Ferrara", "pld": "13", "w": "4", "d": "4", "l": "5", "goals": "19:19", "diff": "0", "pts": "12:14"}, {"pos": "13", "name": "Lazio Roma", "pld": "13", "w": "4", "d": "3", "l": "6", "goals": "14:15", "diff": "-1", "pts": "11:15"}, {"pos": "14", "name": "Genoa CFC", "pld": "13", "w": "5", "d": "1", "l": "7", "goals": "21:24", "diff": "-3", "pts": "11:15"}, {"pos": "15", "name": "Bologna FC", "pld": "13", "w": "4", "d": "2", "l": "7", "goals": "22:25", "diff": "-3", "pts": "10:16"}, {"pos": "16", "name": "Novara Calcio", "pld": "13", "w": "2", "d": "6", "l": "5", "goals": "16:19", "diff": "-3", "pts": "10:16"}, {"pos": "17", "name": "Unione Triestina", "pld": "13", "w": "3", "d": "2", "l": "8", "goals": "7:24", "diff": "-17", "pts": "8:18"}, {"pos": "18", "name": "Aurora Pro Patria", "pld": "13", "w": "1", "d": "3", "l": "9", "goals": "12:41", "diff": "-29", "pts": "5:21"}]