[{"pos": "1", "name": "AC Milan", "pld": "27", "w": "18", "d": "5", "l": "4", "goals": "56:29", "diff": "27", "pts": "41:13"}, {"pos": "2", "name": "ACF Fiorentina", "pld": "27", "w": "13", "d": "7", "l": "7", "goals": "45:33", "diff": "12", "pts": "33:21"}, {"pos": "3", "name": "Inter", "pld": "27", "w": "9", "d": "13", "l": "5", "goals": "39:32", "diff": "7", "pts": "31:23"}, {"pos": "4", "name": "Lazio Roma", "pld": "27", "w": "11", "d": "9", "l": "7", "goals": "36:32", "diff": "4", "pts": "31:23"}, {"pos": "5", "name": "Sampdoria", "pld": "27", "w": "9", "d": "11", "l": "7", "goals": "47:41", "diff": "6", "pts": "29:25"}, {"pos": "6", "name": "Udinese Calcio", "pld": "27", "w": "12", "d": "5", "l": "10", "goals": "45:47", "diff": "-2", "pts": "29:25"}, {"pos": "7", "name": "AS Roma", "pld": "27", "w": "9", "d": "10", "l": "8", "goals": "43:32", "diff": "11", "pts": "28:26"}, {"pos": "8", "name": "SPAL 1907 Ferrara", "pld": "27", "w": "12", "d": "4", "l": "11", "goals": "32:36", "diff": "-4", "pts": "28:26"}, {"pos": "9", "name": "SSC Napoli", "pld": "27", "w": "9", "d": "9", "l": "9", "goals": "31:33", "diff": "-2", "pts": "27:27"}, {"pos": "10", "name": "Bologna FC", "pld": "27", "w": "7", "d": "11", "l": "9", "goals": "36:32", "diff": "4", "pts": "25:29"}, {"pos": "11", "name": "Calcio Padova", "pld": "27", "w": "7", "d": "11", "l": "9", "goals": "27:32", "diff": "-5", "pts": "25:29"}, {"pos": "12", "name": "Unione Triestina", "pld": "27", "w": "8", "d": "9", "l": "10", "goals": "25:31", "diff": "-6", "pts": "25:29"}, {"pos": "13", "name": "Juventus", "pld": "27", "w": "7", "d": "10", "l": "10", "goals": "37:40", "diff": "-3", "pts": "24:30"}, {"pos": "14", "name": "Torino FC", "pld": "27", "w": "9", "d": "6", "l": "12", "goals": "30:33", "diff": "-3", "pts": "24:30"}, {"pos": "15", "name": "Lanerossi Vicenza", "pld": "27", "w": "7", "d": "8", "l": "12", "goals": "34:43", "diff": "-9", "pts": "22:32"}, {"pos": "16", "name": "Atalanta", "pld": "27", "w": "5", "d": "12", "l": "10", "goals": "28:38", "diff": "-10", "pts": "22:32"}, {"pos": "17", "name": "Genoa CFC", "pld": "27", "w": "6", "d": "10", "l": "11", "goals": "26:38", "diff": "-12", "pts": "22:32"}, {"pos": "18", "name": "US Palermo", "pld": "27", "w": "6", "d": "8", "l": "13", "goals": "23:38", "diff": "-15", "pts": "20:34"}]