[{"pos": "1", "name": "AC Milan", "pld": "17", "w": "11", "d": "4", "l": "2", "goals": "37:17", "diff": "20", "pts": "26:8"}, {"pos": "2", "name": "Juventus", "pld": "17", "w": "9", "d": "7", "l": "1", "goals": "23:9", "diff": "14", "pts": "25:9"}, {"pos": "3", "name": "Lazio Roma", "pld": "17", "w": "7", "d": "9", "l": "1", "goals": "18:10", "diff": "8", "pts": "23:11"}, {"pos": "4", "name": "Inter", "pld": "17", "w": "9", "d": "4", "l": "4", "goals": "21:10", "diff": "11", "pts": "22:12"}, {"pos": "5", "name": "ACF Fiorentina", "pld": "17", "w": "8", "d": "4", "l": "5", "goals": "21:16", "diff": "5", "pts": "20:14"}, {"pos": "6", "name": "Cagliari Calcio", "pld": "17", "w": "5", "d": "7", "l": "5", "goals": "15:13", "diff": "2", "pts": "17:17"}, {"pos": "7", "name": "Torino FC", "pld": "17", "w": "6", "d": "4", "l": "7", "goals": "16:13", "diff": "3", "pts": "16:18"}, {"pos": "8", "name": "AS Roma", "pld": "17", "w": "5", "d": "6", "l": "6", "goals": "18:16", "diff": "2", "pts": "16:18"}, {"pos": "9", "name": "Bologna FC", "pld": "17", "w": "6", "d": "4", "l": "7", "goals": "13:17", "diff": "-4", "pts": "16:18"}, {"pos": "10", "name": "Hellas Verona", "pld": "17", "w": "3", "d": "9", "l": "5", "goals": "14:16", "diff": "-2", "pts": "15:19"}, {"pos": "11", "name": "SSC Napoli", "pld": "17", "w": "4", "d": "7", "l": "6", "goals": "9:12", "diff": "-3", "pts": "15:19"}, {"pos": "12", "name": "Atalanta", "pld": "17", "w": "2", "d": "10", "l": "5", "goals": "8:17", "diff": "-9", "pts": "14:20"}, {"pos": "13", "name": "Sampdoria", "pld": "17", "w": "2", "d": "8", "l": "7", "goals": "7:15", "diff": "-8", "pts": "12:22"}, {"pos": "14", "name": "Ternana Calcio", "pld": "17", "w": "3", "d": "6", "l": "8", "goals": "12:23", "diff": "-11", "pts": "12:22"}, {"pos": "15", "name": "Lanerossi Vicenza", "pld": "17", "w": "3", "d": "6", "l": "8", "goals": "7:20", "diff": "-13", "pts": "12:22"}, {"pos": "16", "name": "SSC Palermo", "pld": "17", "w": "3", "d": "5", "l": "9", "goals": "6:21", "diff": "-15", "pts": "11:23"}]