[{"pos": "1", "name": "ACF Fiorentina", "pld": "7", "w": "6", "d": "0", "l": "1", "goals": "14:4", "diff": "10", "pts": "18"}, {"pos": "2", "name": "Inter", "pld": "7", "w": "5", "d": "1", "l": "1", "goals": "8:6", "diff": "2", "pts": "16"}, {"pos": "3", "name": "Lazio Roma", "pld": "7", "w": "5", "d": "0", "l": "2", "goals": "10:11", "diff": "-1", "pts": "15"}, {"pos": "4", "name": "AS Roma", "pld": "7", "w": "4", "d": "2", "l": "1", "goals": "17:9", "diff": "8", "pts": "14"}, {"pos": "5", "name": "Torino FC", "pld": "7", "w": "4", "d": "1", "l": "2", "goals": "12:8", "diff": "4", "pts": "13"}, {"pos": "6", "name": "SSC Napoli", "pld": "7", "w": "3", "d": "3", "l": "1", "goals": "16:7", "diff": "9", "pts": "12"}, {"pos": "7", "name": "Chievo Verona", "pld": "7", "w": "3", "d": "3", "l": "1", "goals": "11:5", "diff": "6", "pts": "12"}, {"pos": "8", "name": "Sassuolo Calcio", "pld": "7", "w": "3", "d": "3", "l": "1", "goals": "9:7", "diff": "2", "pts": "12"}, {"pos": "9", "name": "Sampdoria", "pld": "7", "w": "3", "d": "2", "l": "2", "goals": "13:10", "diff": "3", "pts": "11"}, {"pos": "10", "name": "Atalanta", "pld": "7", "w": "3", "d": "2", "l": "2", "goals": "8:8", "diff": "0", "pts": "11"}, {"pos": "11", "name": "AC Milan", "pld": "7", "w": "3", "d": "0", "l": "4", "goals": "8:13", "diff": "-5", "pts": "9"}, {"pos": "12", "name": "Juventus", "pld": "7", "w": "2", "d": "2", "l": "3", "goals": "9:8", "diff": "1", "pts": "8"}, {"pos": "13", "name": "Empoli FC", "pld": "7", "w": "2", "d": "1", "l": "4", "goals": "7:11", "diff": "-4", "pts": "7"}, {"pos": "14", "name": "Genoa CFC", "pld": "7", "w": "2", "d": "1", "l": "4", "goals": "4:7", "diff": "-3", "pts": "7"}, {"pos": "15", "name": "US Palermo", "pld": "7", "w": "2", "d": "1", "l": "4", "goals": "9:12", "diff": "-3", "pts": "7"}, {"pos": "16", "name": "Udinese Calcio", "pld": "7", "w": "2", "d": "1", "l": "4", "goals": "7:10", "diff": "-3", "pts": "7"}, {"pos": "17", "name": "Carpi FC", "pld": "7", "w": "1", "d": "2", "l": "4", "goals": "8:16", "diff": "-8", "pts": "5"}, {"pos": "18", "name": "Hellas Verona", "pld": "7", "w": "0", "d": "4", "l": "3", "goals": "6:10", "diff": "-4", "pts": "4"}, {"pos": "19", "name": "Frosinone Calcio", "pld": "7", "w": "1", "d": "1", "l": "5", "goals": "4:10", "diff": "-6", "pts": "4"}, {"pos": "20", "name": "Bologna FC", "pld": "7", "w": "1", "d": "0", "l": "6", "goals": "4:12", "diff": "-8", "pts": "3"}]