[{"pos": "1", "name": "AC Milan", "pld": "29", "w": "19", "d": "8", "l": "2", "goals": "33:11", "diff": "22", "pts": "46:12"}, {"pos": "2", "name": "Juventus", "pld": "29", "w": "14", "d": "11", "l": "4", "goals": "50:24", "diff": "26", "pts": "39:19"}, {"pos": "3", "name": "Sampdoria", "pld": "29", "w": "17", "d": "5", "l": "7", "goals": "56:32", "diff": "24", "pts": "39:19"}, {"pos": "4", "name": "Parma AC", "pld": "29", "w": "16", "d": "5", "l": "8", "goals": "46:29", "diff": "17", "pts": "37:21"}, {"pos": "5", "name": "Lazio Roma", "pld": "29", "w": "14", "d": "9", "l": "6", "goals": "43:29", "diff": "14", "pts": "37:21"}, {"pos": "6", "name": "Torino FC", "pld": "29", "w": "10", "d": "10", "l": "9", "goals": "35:29", "diff": "6", "pts": "30:28"}, {"pos": "7", "name": "SSC Napoli", "pld": "29", "w": "10", "d": "10", "l": "9", "goals": "37:33", "diff": "4", "pts": "30:28"}, {"pos": "8", "name": "Inter", "pld": "29", "w": "10", "d": "8", "l": "11", "goals": "38:36", "diff": "2", "pts": "28:30"}, {"pos": "9", "name": "US Cremonese", "pld": "29", "w": "9", "d": "9", "l": "11", "goals": "35:35", "diff": "0", "pts": "27:31"}, {"pos": "10", "name": "US Foggia", "pld": "29", "w": "7", "d": "13", "l": "9", "goals": "38:41", "diff": "-3", "pts": "27:31"}, {"pos": "11", "name": "Genoa CFC", "pld": "29", "w": "7", "d": "13", "l": "9", "goals": "27:33", "diff": "-6", "pts": "27:31"}, {"pos": "12", "name": "Piacenza Calcio", "pld": "29", "w": "8", "d": "11", "l": "10", "goals": "30:38", "diff": "-8", "pts": "27:31"}, {"pos": "13", "name": "Cagliari Calcio", "pld": "29", "w": "8", "d": "11", "l": "10", "goals": "34:43", "diff": "-9", "pts": "27:31"}, {"pos": "14", "name": "AS Roma", "pld": "29", "w": "6", "d": "14", "l": "9", "goals": "24:27", "diff": "-3", "pts": "26:32"}, {"pos": "15", "name": "AC Reggiana", "pld": "29", "w": "7", "d": "10", "l": "12", "goals": "22:31", "diff": "-9", "pts": "24:34"}, {"pos": "16", "name": "Udinese Calcio", "pld": "29", "w": "6", "d": "11", "l": "12", "goals": "26:41", "diff": "-15", "pts": "23:35"}, {"pos": "17", "name": "Atalanta", "pld": "29", "w": "4", "d": "9", "l": "16", "goals": "29:57", "diff": "-28", "pts": "17:41"}, {"pos": "18", "name": "US Lecce", "pld": "29", "w": "3", "d": "5", "l": "21", "goals": "24:58", "diff": "-34", "pts": "11:47"}]