[{"pos": "1", "name": "Juventus", "pld": "31", "w": "24", "d": "3", "l": "4", "goals": "65:30", "diff": "35", "pts": "75"}, {"pos": "2", "name": "Lazio Roma", "pld": "31", "w": "21", "d": "5", "l": "5", "goals": "67:33", "diff": "34", "pts": "68"}, {"pos": "3", "name": "Atalanta", "pld": "31", "w": "20", "d": "6", "l": "5", "goals": "85:39", "diff": "46", "pts": "66"}, {"pos": "4", "name": "Inter", "pld": "31", "w": "19", "d": "8", "l": "4", "goals": "65:33", "diff": "32", "pts": "65"}, {"pos": "5", "name": "AS Roma", "pld": "31", "w": "15", "d": "6", "l": "10", "goals": "56:43", "diff": "13", "pts": "51"}, {"pos": "6", "name": "SSC Napoli", "pld": "31", "w": "15", "d": "6", "l": "10", "goals": "50:41", "diff": "9", "pts": "51"}, {"pos": "7", "name": "AC Milan", "pld": "31", "w": "14", "d": "7", "l": "10", "goals": "43:39", "diff": "4", "pts": "49"}, {"pos": "8", "name": "Sassuolo Calcio", "pld": "31", "w": "12", "d": "7", "l": "12", "goals": "57:53", "diff": "4", "pts": "43"}, {"pos": "9", "name": "Hellas Verona", "pld": "31", "w": "11", "d": "10", "l": "10", "goals": "39:38", "diff": "1", "pts": "43"}, {"pos": "10", "name": "Bologna FC", "pld": "31", "w": "11", "d": "8", "l": "12", "goals": "44:49", "diff": "-5", "pts": "41"}, {"pos": "11", "name": "Cagliari Calcio", "pld": "31", "w": "10", "d": "10", "l": "11", "goals": "48:46", "diff": "2", "pts": "40"}, {"pos": "12", "name": "Parma Calcio 1913", "pld": "31", "w": "11", "d": "6", "l": "14", "goals": "42:42", "diff": "0", "pts": "39"}, {"pos": "13", "name": "ACF Fiorentina", "pld": "31", "w": "8", "d": "11", "l": "12", "goals": "37:43", "diff": "-6", "pts": "35"}, {"pos": "14", "name": "Udinese Calcio", "pld": "31", "w": "9", "d": "8", "l": "14", "goals": "30:43", "diff": "-13", "pts": "35"}, {"pos": "15", "name": "Torino FC", "pld": "31", "w": "10", "d": "4", "l": "17", "goals": "37:57", "diff": "-20", "pts": "34"}, {"pos": "16", "name": "Sampdoria", "pld": "31", "w": "9", "d": "5", "l": "17", "goals": "36:53", "diff": "-17", "pts": "32"}, {"pos": "17", "name": "US Lecce", "pld": "31", "w": "7", "d": "7", "l": "17", "goals": "40:71", "diff": "-31", "pts": "28"}, {"pos": "18", "name": "Genoa CFC", "pld": "31", "w": "6", "d": "9", "l": "16", "goals": "38:60", "diff": "-22", "pts": "27"}, {"pos": "19", "name": "Brescia Calcio", "pld": "31", "w": "5", "d": "6", "l": "20", "goals": "28:61", "diff": "-33", "pts": "21"}, {"pos": "20", "name": "SPAL 2013 Ferrara", "pld": "31", "w": "5", "d": "4", "l": "22", "goals": "23:56", "diff": "-33", "pts": "19"}]