[{"pos": "1", "name": "AC Milan", "pld": "16", "w": "12", "d": "4", "l": "0", "goals": "32:10", "diff": "22", "pts": "28:4"}, {"pos": "2", "name": "Inter", "pld": "16", "w": "9", "d": "6", "l": "1", "goals": "24:15", "diff": "9", "pts": "24:8"}, {"pos": "3", "name": "Juventus", "pld": "16", "w": "7", "d": "7", "l": "2", "goals": "18:11", "diff": "7", "pts": "21:11"}, {"pos": "4", "name": "ACF Fiorentina", "pld": "16", "w": "7", "d": "6", "l": "3", "goals": "21:18", "diff": "3", "pts": "20:12"}, {"pos": "5", "name": "Torino FC", "pld": "16", "w": "6", "d": "7", "l": "3", "goals": "21:14", "diff": "7", "pts": "19:13"}, {"pos": "6", "name": "Bologna FC", "pld": "16", "w": "7", "d": "4", "l": "5", "goals": "20:12", "diff": "8", "pts": "18:14"}, {"pos": "7", "name": "AS Roma", "pld": "16", "w": "4", "d": "8", "l": "4", "goals": "20:18", "diff": "2", "pts": "16:16"}, {"pos": "8", "name": "Calcio Catania", "pld": "16", "w": "5", "d": "5", "l": "6", "goals": "19:21", "diff": "-2", "pts": "15:17"}, {"pos": "9", "name": "Lanerossi Vicenza", "pld": "16", "w": "5", "d": "5", "l": "6", "goals": "15:17", "diff": "-2", "pts": "15:17"}, {"pos": "10", "name": "Atalanta", "pld": "16", "w": "4", "d": "7", "l": "5", "goals": "8:10", "diff": "-2", "pts": "15:17"}, {"pos": "11", "name": "US Foggia", "pld": "16", "w": "5", "d": "5", "l": "6", "goals": "11:15", "diff": "-4", "pts": "15:17"}, {"pos": "12", "name": "Sampdoria", "pld": "16", "w": "4", "d": "6", "l": "6", "goals": "13:16", "diff": "-3", "pts": "14:18"}, {"pos": "13", "name": "AS Varese 1910", "pld": "16", "w": "3", "d": "8", "l": "5", "goals": "16:21", "diff": "-5", "pts": "14:18"}, {"pos": "14", "name": "Lazio Roma", "pld": "16", "w": "3", "d": "7", "l": "6", "goals": "13:15", "diff": "-2", "pts": "13:19"}, {"pos": "15", "name": "Genoa CFC", "pld": "16", "w": "2", "d": "8", "l": "6", "goals": "11:17", "diff": "-6", "pts": "12:20"}, {"pos": "16", "name": "A.C.R. Messina", "pld": "16", "w": "3", "d": "5", "l": "8", "goals": "10:20", "diff": "-10", "pts": "11:21"}, {"pos": "17", "name": "AC Mantova", "pld": "16", "w": "2", "d": "5", "l": "9", "goals": "7:17", "diff": "-10", "pts": "9:23"}, {"pos": "18", "name": "Cagliari Calcio", "pld": "16", "w": "1", "d": "7", "l": "8", "goals": "9:21", "diff": "-12", "pts": "9:23"}]