[{"pos": "1", "name": "Cagliari Calcio", "pld": "21", "w": "12", "d": "7", "l": "2", "goals": "28:8", "diff": "20", "pts": "31:11"}, {"pos": "2", "name": "Juventus", "pld": "21", "w": "13", "d": "4", "l": "4", "goals": "35:11", "diff": "24", "pts": "30:12"}, {"pos": "3", "name": "ACF Fiorentina", "pld": "21", "w": "12", "d": "4", "l": "5", "goals": "31:23", "diff": "8", "pts": "28:14"}, {"pos": "4", "name": "AC Milan", "pld": "21", "w": "10", "d": "7", "l": "4", "goals": "30:15", "diff": "15", "pts": "27:15"}, {"pos": "5", "name": "Inter", "pld": "21", "w": "10", "d": "7", "l": "4", "goals": "26:15", "diff": "11", "pts": "27:15"}, {"pos": "6", "name": "SSC Napoli", "pld": "21", "w": "9", "d": "6", "l": "6", "goals": "20:14", "diff": "6", "pts": "24:18"}, {"pos": "7", "name": "AS Roma", "pld": "21", "w": "7", "d": "7", "l": "7", "goals": "20:26", "diff": "-6", "pts": "21:21"}, {"pos": "8", "name": "Lanerossi Vicenza", "pld": "21", "w": "8", "d": "4", "l": "9", "goals": "24:22", "diff": "2", "pts": "20:22"}, {"pos": "9", "name": "Torino FC", "pld": "21", "w": "7", "d": "6", "l": "8", "goals": "15:22", "diff": "-7", "pts": "20:22"}, {"pos": "10", "name": "Bologna FC", "pld": "21", "w": "4", "d": "11", "l": "6", "goals": "16:16", "diff": "0", "pts": "19:23"}, {"pos": "11", "name": "Hellas Verona", "pld": "21", "w": "5", "d": "9", "l": "7", "goals": "17:20", "diff": "-3", "pts": "19:23"}, {"pos": "12", "name": "Lazio Roma", "pld": "21", "w": "7", "d": "3", "l": "11", "goals": "16:25", "diff": "-9", "pts": "17:25"}, {"pos": "13", "name": "AS Bari", "pld": "21", "w": "4", "d": "7", "l": "10", "goals": "7:22", "diff": "-15", "pts": "15:27"}, {"pos": "14", "name": "SSC Palermo", "pld": "21", "w": "4", "d": "6", "l": "11", "goals": "17:31", "diff": "-14", "pts": "14:28"}, {"pos": "15", "name": "Sampdoria", "pld": "21", "w": "2", "d": "9", "l": "10", "goals": "14:28", "diff": "-14", "pts": "13:29"}, {"pos": "16", "name": "Brescia Calcio", "pld": "21", "w": "2", "d": "7", "l": "12", "goals": "10:28", "diff": "-18", "pts": "11:31"}]