[{"pos": "1", "name": "Juventus", "pld": "13", "w": "10", "d": "1", "l": "2", "goals": "28:10", "diff": "18", "pts": "21:5"}, {"pos": "2", "name": "AS Roma", "pld": "13", "w": "8", "d": "4", "l": "1", "goals": "29:13", "diff": "16", "pts": "20:6"}, {"pos": "3", "name": "Bologna FC", "pld": "13", "w": "9", "d": "1", "l": "3", "goals": "36:14", "diff": "22", "pts": "19:7"}, {"pos": "4", "name": "SSC Napoli", "pld": "13", "w": "9", "d": "1", "l": "3", "goals": "25:16", "diff": "9", "pts": "19:7"}, {"pos": "5", "name": "Lazio Roma", "pld": "13", "w": "8", "d": "2", "l": "3", "goals": "20:13", "diff": "7", "pts": "18:8"}, {"pos": "6", "name": "Genova 1893 Circolo del Calcio", "pld": "13", "w": "8", "d": "0", "l": "5", "goals": "24:22", "diff": "2", "pts": "16:10"}, {"pos": "7", "name": "Modena FC", "pld": "13", "w": "6", "d": "2", "l": "5", "goals": "23:20", "diff": "3", "pts": "14:12"}, {"pos": "8", "name": "US Alessandria 1912", "pld": "13", "w": "6", "d": "0", "l": "7", "goals": "22:19", "diff": "3", "pts": "12:14"}, {"pos": "9", "name": "Torino FC", "pld": "13", "w": "5", "d": "2", "l": "6", "goals": "17:16", "diff": "1", "pts": "12:14"}, {"pos": "10", "name": "Brescia Calcio", "pld": "13", "w": "5", "d": "2", "l": "6", "goals": "17:25", "diff": "-8", "pts": "12:14"}, {"pos": "11", "name": "Pro Vercelli", "pld": "13", "w": "4", "d": "3", "l": "6", "goals": "15:19", "diff": "-4", "pts": "11:15"}, {"pos": "12", "name": "Inter", "pld": "13", "w": "3", "d": "5", "l": "5", "goals": "17:25", "diff": "-8", "pts": "11:15"}, {"pos": "13", "name": "AC Milan", "pld": "13", "w": "4", "d": "2", "l": "7", "goals": "12:18", "diff": "-6", "pts": "10:16"}, {"pos": "14", "name": "Unione Triestina", "pld": "13", "w": "3", "d": "3", "l": "7", "goals": "11:18", "diff": "-7", "pts": "9:17"}, {"pos": "15", "name": "Aurora Pro Patria", "pld": "13", "w": "4", "d": "1", "l": "8", "goals": "15:28", "diff": "-13", "pts": "9:17"}, {"pos": "16", "name": "Casale", "pld": "13", "w": "3", "d": "2", "l": "8", "goals": "15:27", "diff": "-12", "pts": "8:18"}, {"pos": "17", "name": "Legnano", "pld": "13", "w": "2", "d": "3", "l": "8", "goals": "10:21", "diff": "-11", "pts": "7:19"}, {"pos": "18", "name": "US Livorno", "pld": "13", "w": "2", "d": "2", "l": "9", "goals": "12:24", "diff": "-12", "pts": "6:20"}]