[{"pos": "1", "name": "AC Milan", "pld": "16", "w": "10", "d": "4", "l": "2", "goals": "22:8", "diff": "14", "pts": "24:8"}, {"pos": "2", "name": "Juventus", "pld": "16", "w": "11", "d": "2", "l": "3", "goals": "28:15", "diff": "13", "pts": "24:8"}, {"pos": "3", "name": "Cagliari Calcio", "pld": "16", "w": "8", "d": "6", "l": "2", "goals": "18:9", "diff": "9", "pts": "22:10"}, {"pos": "4", "name": "Inter", "pld": "16", "w": "8", "d": "5", "l": "3", "goals": "32:13", "diff": "19", "pts": "21:11"}, {"pos": "5", "name": "AS Roma", "pld": "16", "w": "9", "d": "3", "l": "4", "goals": "22:19", "diff": "3", "pts": "21:11"}, {"pos": "6", "name": "ACF Fiorentina", "pld": "16", "w": "7", "d": "6", "l": "3", "goals": "15:11", "diff": "4", "pts": "20:12"}, {"pos": "7", "name": "Torino FC", "pld": "16", "w": "7", "d": "6", "l": "3", "goals": "18:15", "diff": "3", "pts": "20:12"}, {"pos": "8", "name": "SSC Napoli", "pld": "16", "w": "4", "d": "9", "l": "3", "goals": "18:17", "diff": "1", "pts": "17:15"}, {"pos": "9", "name": "Sampdoria", "pld": "16", "w": "5", "d": "6", "l": "5", "goals": "15:17", "diff": "-2", "pts": "16:16"}, {"pos": "10", "name": "Atalanta", "pld": "16", "w": "6", "d": "2", "l": "8", "goals": "12:15", "diff": "-3", "pts": "14:18"}, {"pos": "11", "name": "Bologna FC", "pld": "16", "w": "4", "d": "4", "l": "8", "goals": "13:20", "diff": "-7", "pts": "12:20"}, {"pos": "12", "name": "Lanerossi Vicenza", "pld": "16", "w": "4", "d": "3", "l": "9", "goals": "18:24", "diff": "-6", "pts": "11:21"}, {"pos": "13", "name": "US Catanzaro", "pld": "16", "w": "1", "d": "9", "l": "6", "goals": "9:17", "diff": "-8", "pts": "11:21"}, {"pos": "14", "name": "Hellas Verona", "pld": "16", "w": "2", "d": "7", "l": "7", "goals": "10:20", "diff": "-10", "pts": "11:21"}, {"pos": "15", "name": "AC Mantova", "pld": "16", "w": "2", "d": "3", "l": "11", "goals": "12:26", "diff": "-14", "pts": "7:25"}, {"pos": "16", "name": "AS Varese 1910", "pld": "16", "w": "0", "d": "5", "l": "11", "goals": "7:23", "diff": "-16", "pts": "5:27"}]