[{"pos": "1", "name": "AC Milan", "pld": "32", "w": "24", "d": "7", "l": "1", "goals": "60:20", "diff": "40", "pts": "79"}, {"pos": "2", "name": "AS Roma", "pld": "32", "w": "21", "d": "7", "l": "4", "goals": "67:16", "diff": "51", "pts": "70"}, {"pos": "3", "name": "Juventus", "pld": "32", "w": "19", "d": "6", "l": "7", "goals": "62:41", "diff": "21", "pts": "63"}, {"pos": "4", "name": "Parma AC", "pld": "32", "w": "15", "d": "10", "l": "7", "goals": "53:42", "diff": "11", "pts": "55"}, {"pos": "5", "name": "Inter", "pld": "32", "w": "15", "d": "8", "l": "9", "goals": "55:35", "diff": "20", "pts": "53"}, {"pos": "6", "name": "Lazio Roma", "pld": "32", "w": "15", "d": "8", "l": "9", "goals": "49:35", "diff": "14", "pts": "53"}, {"pos": "7", "name": "Udinese Calcio", "pld": "32", "w": "13", "d": "10", "l": "9", "goals": "40:35", "diff": "5", "pts": "49"}, {"pos": "8", "name": "Sampdoria", "pld": "32", "w": "11", "d": "12", "l": "9", "goals": "40:40", "diff": "0", "pts": "45"}, {"pos": "9", "name": "Chievo Verona", "pld": "32", "w": "10", "d": "10", "l": "12", "goals": "33:35", "diff": "-2", "pts": "40"}, {"pos": "10", "name": "Bologna FC", "pld": "32", "w": "10", "d": "8", "l": "14", "goals": "43:50", "diff": "-7", "pts": "38"}, {"pos": "11", "name": "Brescia Calcio", "pld": "32", "w": "8", "d": "13", "l": "11", "goals": "48:52", "diff": "-4", "pts": "37"}, {"pos": "12", "name": "US Lecce", "pld": "32", "w": "10", "d": "7", "l": "15", "goals": "40:54", "diff": "-14", "pts": "37"}, {"pos": "13", "name": "AC Siena", "pld": "32", "w": "7", "d": "10", "l": "15", "goals": "37:50", "diff": "-13", "pts": "31"}, {"pos": "14", "name": "Reggina Calcio", "pld": "32", "w": "5", "d": "16", "l": "11", "goals": "26:42", "diff": "-16", "pts": "31"}, {"pos": "15", "name": "Modena FC", "pld": "32", "w": "6", "d": "12", "l": "14", "goals": "25:41", "diff": "-16", "pts": "30"}, {"pos": "16", "name": "Empoli FC", "pld": "32", "w": "7", "d": "9", "l": "16", "goals": "23:49", "diff": "-26", "pts": "30"}, {"pos": "17", "name": "AC Perugia", "pld": "32", "w": "4", "d": "14", "l": "14", "goals": "40:55", "diff": "-15", "pts": "26"}, {"pos": "18", "name": "Ancona Calcio", "pld": "32", "w": "1", "d": "7", "l": "24", "goals": "19:68", "diff": "-49", "pts": "10"}]