[{"pos": "1", "name": "AC Milan", "pld": "21", "w": "13", "d": "7", "l": "1", "goals": "33:13", "diff": "20", "pts": "46"}, {"pos": "2", "name": "ACF Fiorentina", "pld": "21", "w": "12", "d": "5", "l": "4", "goals": "35:20", "diff": "15", "pts": "41"}, {"pos": "3", "name": "Parma AC", "pld": "21", "w": "10", "d": "8", "l": "3", "goals": "31:18", "diff": "13", "pts": "38"}, {"pos": "4", "name": "Juventus", "pld": "21", "w": "10", "d": "5", "l": "6", "goals": "34:22", "diff": "12", "pts": "35"}, {"pos": "5", "name": "Lazio Roma", "pld": "21", "w": "9", "d": "6", "l": "6", "goals": "41:25", "diff": "16", "pts": "33"}, {"pos": "6", "name": "AS Roma", "pld": "21", "w": "8", "d": "7", "l": "6", "goals": "28:21", "diff": "7", "pts": "31"}, {"pos": "7", "name": "Inter", "pld": "21", "w": "7", "d": "8", "l": "6", "goals": "28:18", "diff": "10", "pts": "29"}, {"pos": "8", "name": "Vicenza Calcio", "pld": "21", "w": "7", "d": "8", "l": "6", "goals": "22:21", "diff": "1", "pts": "29"}, {"pos": "9", "name": "SSC Napoli", "pld": "21", "w": "7", "d": "8", "l": "6", "goals": "22:25", "diff": "-3", "pts": "29"}, {"pos": "10", "name": "Sampdoria", "pld": "21", "w": "7", "d": "7", "l": "7", "goals": "30:30", "diff": "0", "pts": "28"}, {"pos": "11", "name": "Udinese Calcio", "pld": "21", "w": "7", "d": "6", "l": "8", "goals": "25:29", "diff": "-4", "pts": "27"}, {"pos": "12", "name": "Atalanta", "pld": "21", "w": "7", "d": "4", "l": "10", "goals": "23:33", "diff": "-10", "pts": "25"}, {"pos": "13", "name": "Cagliari Calcio", "pld": "21", "w": "7", "d": "3", "l": "11", "goals": "18:33", "diff": "-15", "pts": "24"}, {"pos": "14", "name": "Piacenza Calcio", "pld": "21", "w": "6", "d": "5", "l": "10", "goals": "21:36", "diff": "-15", "pts": "23"}, {"pos": "15", "name": "Calcio Padova", "pld": "21", "w": "6", "d": "3", "l": "12", "goals": "25:35", "diff": "-10", "pts": "21"}, {"pos": "16", "name": "Torino FC", "pld": "21", "w": "4", "d": "9", "l": "8", "goals": "21:32", "diff": "-11", "pts": "21"}, {"pos": "17", "name": "AS Bari", "pld": "21", "w": "4", "d": "6", "l": "11", "goals": "30:44", "diff": "-14", "pts": "18"}, {"pos": "18", "name": "US Cremonese", "pld": "21", "w": "2", "d": "7", "l": "12", "goals": "23:35", "diff": "-12", "pts": "13"}]