[{"pos": "1", "name": "Inter", "pld": "19", "w": "12", "d": "6", "l": "1", "goals": "43:14", "diff": "29", "pts": "30:8"}, {"pos": "2", "name": "Juventus", "pld": "19", "w": "11", "d": "4", "l": "4", "goals": "53:23", "diff": "30", "pts": "26:12"}, {"pos": "3", "name": "Bologna FC", "pld": "19", "w": "10", "d": "4", "l": "5", "goals": "32:21", "diff": "11", "pts": "24:14"}, {"pos": "4", "name": "AC Milan", "pld": "19", "w": "9", "d": "4", "l": "6", "goals": "38:25", "diff": "13", "pts": "22:16"}, {"pos": "5", "name": "SSC Napoli", "pld": "19", "w": "8", "d": "6", "l": "5", "goals": "21:19", "diff": "2", "pts": "22:16"}, {"pos": "6", "name": "AS Roma", "pld": "19", "w": "8", "d": "4", "l": "7", "goals": "28:14", "diff": "14", "pts": "20:18"}, {"pos": "7", "name": "Pro Vercelli", "pld": "19", "w": "7", "d": "6", "l": "6", "goals": "24:22", "diff": "2", "pts": "20:18"}, {"pos": "8", "name": "Lazio Roma", "pld": "19", "w": "7", "d": "6", "l": "6", "goals": "29:30", "diff": "-1", "pts": "20:18"}, {"pos": "9", "name": "ACF Fiorentina", "pld": "19", "w": "9", "d": "2", "l": "8", "goals": "32:37", "diff": "-5", "pts": "20:18"}, {"pos": "10", "name": "Palmero FC", "pld": "19", "w": "7", "d": "4", "l": "8", "goals": "22:28", "diff": "-6", "pts": "18:20"}, {"pos": "11", "name": "Unione Triestina", "pld": "19", "w": "4", "d": "9", "l": "6", "goals": "19:21", "diff": "-2", "pts": "17:21"}, {"pos": "12", "name": "US Livorno", "pld": "19", "w": "4", "d": "9", "l": "6", "goals": "23:31", "diff": "-8", "pts": "17:21"}, {"pos": "13", "name": "Brescia Calcio", "pld": "19", "w": "6", "d": "5", "l": "8", "goals": "17:26", "diff": "-9", "pts": "17:21"}, {"pos": "14", "name": "Torino FC", "pld": "19", "w": "5", "d": "6", "l": "8", "goals": "24:28", "diff": "-4", "pts": "16:22"}, {"pos": "15", "name": "US Alessandria 1912", "pld": "19", "w": "6", "d": "3", "l": "10", "goals": "29:35", "diff": "-6", "pts": "15:23"}, {"pos": "16", "name": "Genova 1893 Circolo del Calcio", "pld": "19", "w": "5", "d": "5", "l": "9", "goals": "20:34", "diff": "-14", "pts": "15:23"}, {"pos": "17", "name": "Calcio Padova", "pld": "19", "w": "5", "d": "3", "l": "11", "goals": "22:33", "diff": "-11", "pts": "13:25"}, {"pos": "18", "name": "Casale", "pld": "19", "w": "3", "d": "4", "l": "12", "goals": "20:55", "diff": "-35", "pts": "10:28"}]