[{"pos": "1", "name": "Juventus", "pld": "19", "w": "13", "d": "3", "l": "3", "goals": "43:13", "diff": "30", "pts": "29:9"}, {"pos": "2", "name": "Bologna FC", "pld": "19", "w": "9", "d": "9", "l": "1", "goals": "38:14", "diff": "24", "pts": "27:11"}, {"pos": "3", "name": "SSC Napoli", "pld": "19", "w": "11", "d": "4", "l": "4", "goals": "39:21", "diff": "18", "pts": "26:12"}, {"pos": "4", "name": "Inter", "pld": "19", "w": "10", "d": "5", "l": "4", "goals": "47:34", "diff": "13", "pts": "25:13"}, {"pos": "5", "name": "Torino FC", "pld": "19", "w": "9", "d": "6", "l": "4", "goals": "47:28", "diff": "19", "pts": "24:14"}, {"pos": "6", "name": "AS Roma", "pld": "19", "w": "10", "d": "4", "l": "5", "goals": "33:18", "diff": "15", "pts": "24:14"}, {"pos": "7", "name": "ACF Fiorentina", "pld": "19", "w": "8", "d": "4", "l": "7", "goals": "28:23", "diff": "5", "pts": "20:18"}, {"pos": "8", "name": "Genova 1893 Circolo del Calcio", "pld": "19", "w": "8", "d": "3", "l": "8", "goals": "38:35", "diff": "3", "pts": "19:19"}, {"pos": "9", "name": "Calcio Padova", "pld": "19", "w": "6", "d": "7", "l": "6", "goals": "26:24", "diff": "2", "pts": "19:19"}, {"pos": "10", "name": "AC Milan", "pld": "19", "w": "7", "d": "5", "l": "7", "goals": "34:35", "diff": "-1", "pts": "19:19"}, {"pos": "11", "name": "Pro Vercelli", "pld": "19", "w": "7", "d": "3", "l": "9", "goals": "19:29", "diff": "-10", "pts": "17:21"}, {"pos": "12", "name": "Palmero FC", "pld": "19", "w": "6", "d": "4", "l": "9", "goals": "16:31", "diff": "-15", "pts": "16:22"}, {"pos": "13", "name": "Unione Triestina", "pld": "19", "w": "6", "d": "4", "l": "9", "goals": "20:39", "diff": "-19", "pts": "16:22"}, {"pos": "14", "name": "Lazio Roma", "pld": "19", "w": "5", "d": "5", "l": "9", "goals": "23:29", "diff": "-6", "pts": "15:23"}, {"pos": "15", "name": "US Alessandria 1912", "pld": "19", "w": "5", "d": "4", "l": "10", "goals": "19:38", "diff": "-19", "pts": "14:24"}, {"pos": "16", "name": "AS Bari", "pld": "19", "w": "4", "d": "4", "l": "11", "goals": "22:40", "diff": "-18", "pts": "12:26"}, {"pos": "17", "name": "Casale", "pld": "19", "w": "4", "d": "3", "l": "12", "goals": "23:45", "diff": "-22", "pts": "11:27"}, {"pos": "18", "name": "Aurora Pro Patria", "pld": "19", "w": "3", "d": "3", "l": "13", "goals": "21:40", "diff": "-19", "pts": "9:29"}]